ONBFactory/__init__.py
ONBFactory/urls.py
ONBFactory/wsgi.py
ONBFactory/config/__init__.py
ONBFactory/config/common.py
ONBFactory/config/local.py
ONBFactory/config/production.py
backup/__init__.py
backup/admin.py
backup/apps.py
backup/models.py
backup/tests.py
backup/views.py
backup/migrations/__init__.py
common/__init__.py
common/admin.py
common/apps.py
common/tests.py
example_pkg_yanama-0.0.4.dist-info/METADATA
example_pkg_yanama-0.0.4.dist-info/RECORD
example_pkg_yanama-0.0.4.dist-info/WHEEL
example_pkg_yanama-0.0.4.dist-info/top_level.txt
iaas/__init__.py
iaas/admin.py
iaas/apps.py
iaas/chpapi.py
iaas/iaas.py
iaas/iaas_client_factory.py
iaas/networker.py
iaas/tests.py
iaas/vec.py
iaas/xstream.py
iaas/common/__init__.py
iaas/common/constants.py
iaas/common/functions.py
onboarding/__init__.py
onboarding/admin.py
onboarding/apps.py
onboarding/models.py
onboarding/tests.py
onboarding/views.py
onboarding/migrations/__init__.py
saltmanager/__init__.py
saltmanager/admin.py
saltmanager/apps.py
saltmanager/tests.py
